mira_network-0.1.6.dist-info/METADATA
mira_network-0.1.6.dist-info/WHEEL
mira_network-0.1.6.dist-info/entry_points.txt
mira_network-0.1.6.dist-info/licenses/LICENSE
mira_network/__init__.py
mira_network/client.py
mira_network/models.py
mira_network/sync_client.py
mira_network-0.1.6.dist-info/RECORD
