Metadata-Version: 2.1
Name: mira-network
Version: 0.1.6
Summary: Python SDK for Mira Network API
Author-Email: sarim2000 <sarimbleedblue@gmail.com>
License: MIT
Requires-Python: ==3.11.*
Requires-Dist: httpx>=0.28.1
Requires-Dist: pydantic>=2.10.4
Requires-Dist: typing-extensions>=4.8.0
Requires-Dist: requests>=2.32.3
Requires-Dist: pytest-cov>=6.0.0
